inmanta_plugins/platform/__init__.py
inmanta_plugins/platform/setup.cfg
inmanta_plugins/platform/model/_init.cf
inmanta_plugins/platform/templates/user_data.j2
inmanta_module_platform-1.1.15.dist-info/METADATA
inmanta_module_platform-1.1.15.dist-info/WHEEL
inmanta_module_platform-1.1.15.dist-info/top_level.txt
inmanta_module_platform-1.1.15.dist-info/RECORD
