Metadata-Version: 2.1
Name: inmanta-module-platform
Version: 1.1.15
License: ASL 2.0
Requires-Dist: inmanta-module-std >=0.21.0
